provisioner_examples_plugin/__init__.py
provisioner_examples_plugin/main.py
provisioner_examples_plugin/main_fake.py
provisioner_examples_plugin/resources/__init__.py
provisioner_examples_plugin/resources/config.yaml
provisioner_examples_plugin/resources/manifest.json
provisioner_examples_plugin/src/__init__.py
provisioner_examples_plugin/src/anchor/__init__.py
provisioner_examples_plugin/src/anchor/anchor_cmd.py
provisioner_examples_plugin/src/anchor/cli.py
provisioner_examples_plugin/src/ansible/__init__.py
provisioner_examples_plugin/src/ansible/cli.py
provisioner_examples_plugin/src/ansible/hello_world_cmd.py
provisioner_examples_plugin/src/ansible/hello_world_runner.py
provisioner_examples_plugin/src/config/domain/config.py
provisioner_examples_plugin/src/config/domain/config_fakes.py
provisioner_examples_plugin-0.1.11.dist-info/METADATA
provisioner_examples_plugin-0.1.11.dist-info/WHEEL
provisioner_examples_plugin-0.1.11.dist-info/entry_points.txt
provisioner_examples_plugin-0.1.11.dist-info/RECORD
